adls_pandas_utils/__init__.py
adls_pandas_utils/blob_helpers.py
adls_pandas_utils/data_transformations.py
adls_pandas_utils/full_incr_load.py
adls_pandas_utils/utils.py
adls_pandas_utils-0.0.5.dist-info/METADATA
adls_pandas_utils-0.0.5.dist-info/WHEEL
adls_pandas_utils-0.0.5.dist-info/top_level.txt
adls_pandas_utils-0.0.5.dist-info/RECORD
